novelpia/__init__.py
novelpia/errors.py
novelpia/main.py
novelpia_python/__init__.py
novelpia_python/errors.py
novelpia_python/main.py
novelpia-1.0.0.dist-info/LICENSE
novelpia-1.0.0.dist-info/METADATA
novelpia-1.0.0.dist-info/WHEEL
novelpia-1.0.0.dist-info/top_level.txt
novelpia-1.0.0.dist-info/RECORD
