Metadata-Version: 2.1
Name: novelpia
Version: 1.0.0
Summary: 노벨피아 비공식 라이브러리
Home-page: https://github.com/EricAn0630/novelpia
Author: Eric_An0630
Author-email: soochan06@naver.com
License: MIT License
Download-URL: https://github.com/EricAn0630/novepia/archive/1.0.0.tar.gz
Platform: UNKNOWN
Requires-Dist: requests
